ai_transformersx/__init__.py
ai_transformersx/configuration.py
ai_transformersx/dataprocessor.py
ai_transformersx/dataset.py
ai_transformersx/down_tasks.py
ai_transformersx/models.py
ai_transformersx/tasks.py
ai_transformersx/trainer.py
ai_transformersx/trainer_utils.py
ai_transformersx/training_args.py
ai_transformersx/transformersx_base.py
ai_transformersx/data/__init__.py
ai_transformersx/data/data_args.py
ai_transformersx/data/dataprocessor.py
ai_transformersx/data/dataset.py
ai_transformersx/data/task_data_args.py
ai_transformersx/data/task_data_converter.py
ai_transformersx/data/task_data_processor.py
ai_transformersx/data/task_data_store.py
ai_transformersx/data/task_dataset_factory.py
ai_transformersx/examples/__init__.py
ai_transformersx/examples/example_base.py
ai_transformersx/examples/examples_management.py
ai_transformersx/examples/main.py
ai_transformersx/examples/tasks/__init__.py
ai_transformersx/examples/tasks/task_base.py
ai_transformersx/examples/tasks/news_classification/__init__.py
ai_transformersx/examples/tasks/news_classification/general_models.py
ai_transformersx/examples/tasks/news_classification/transformer_models.py
ai_transformersx/examples/tasks/news_segment/__init__.py
ai_transformersx/examples/tasks/news_segment/news_data_processor.py
ai_transformersx/examples/tasks/news_segment/news_segment_task.py
ai_transformersx/examples/tasks/sentiment/__init__.py
ai_transformersx/examples/tasks/sentiment/sentiment_task.py
ai_transformersx/legacy/__init__.py
ai_transformersx/legacy/configuration.py
ai_transformersx/legacy/dataprocessor.py
ai_transformersx/legacy/dataset.py
ai_transformersx/legacy/models.py
ai_transformersx/legacy/tasks.py
ai_transformersx/legacy/trainer.py
ai_transformersx/legacy/trainer_utils.py
ai_transformersx/legacy/training_args.py
ai_transformersx/model/__init__.py
ai_transformersx/model/model_args.py
ai_transformersx/model/model_base.py
ai_transformersx/model/model_utils.py
ai_transformersx/model/modelingx_electra.py
ai_transformersx-0.6.17.dist-info/LICENSE.txt
ai_transformersx-0.6.17.dist-info/METADATA
ai_transformersx-0.6.17.dist-info/WHEEL
ai_transformersx-0.6.17.dist-info/top_level.txt
ai_transformersx-0.6.17.dist-info/RECORD
