Metadata-Version: 2.1
Name: ai-transformersx
Version: 0.6.17
Summary: tools for using huggingface/transformers more easily
Home-page: https://github.com/aicanhelp/ai-transformers
Author: modongsong
Author-email: modongsongml@163.com
License: MIT
Project-URL: Bug Reports, https://github.com/aicanhelp/ai-transformersx/issues
Project-URL: Source, https://github.com/aicanhelp/ai-transformers/
Keywords: deeplearning tools development
Platform: UNKNOWN
Classifier: Development Status :: 3 - Alpha
Classifier: Intended Audience :: Developers
Classifier: Topic :: Software Development :: Build Tools
Classifier: License :: OSI Approved :: MIT License
Classifier: Programming Language :: Python :: 3.5
Classifier: Programming Language :: Python :: 3.6
Classifier: Programming Language :: Python :: 3.7
Classifier: Programming Language :: Python :: 3.8
Requires-Python: >=3.5, <4
Provides-Extra: dev
Requires-Dist: check-manifest ; extra == 'dev'
Provides-Extra: test
Requires-Dist: coverage ; extra == 'test'
Requires-Dist: pytest ; extra == 'test'
